onelab/__init__.py
onelab/gmsh.py
onelab/onelab.py
onelab-0.9.dist-info/LICENSE
onelab-0.9.dist-info/METADATA
onelab-0.9.dist-info/WHEEL
onelab-0.9.dist-info/top_level.txt
onelab-0.9.dist-info/RECORD
