Metadata-Version: 2.1
Name: onelab
Version: 0.9
Summary: A python package to use gmsh and ONELAB via their original python APIs
Home-page: https://github.com/jackbkennedy/onelab
Author: Jack Kennedy
Author-email: jackbkennedy@gmail.com
License: GPL
Platform: UNKNOWN
Classifier: Programming Language :: Python :: 3
Classifier: Operating System :: OS Independent
Requires-Python: >=3.6
Requires-Dist: numpy
Requires-Dist: pandas
